XinshouZhinanDvwa19QuanJibieJiaocheng/README.md
XinshouZhinanDvwa19QuanJibieJiaocheng/__init__.py
XinshouZhinanDvwa19QuanJibieJiaocheng/__main__.py
XinshouZhinanDvwa19QuanJibieJiaocheng/file.epub
XinshouZhinanDvwa19QuanJibieJiaocheng/index.html
XinshouZhinanDvwa19QuanJibieJiaocheng/css/__init__.py
XinshouZhinanDvwa19QuanJibieJiaocheng/css/annotations.css
XinshouZhinanDvwa19QuanJibieJiaocheng/css/main.css
XinshouZhinanDvwa19QuanJibieJiaocheng/css/normalize.css
XinshouZhinanDvwa19QuanJibieJiaocheng/css/popup.css
XinshouZhinanDvwa19QuanJibieJiaocheng/font/__init__.py
XinshouZhinanDvwa19QuanJibieJiaocheng/font/fontello.eot
XinshouZhinanDvwa19QuanJibieJiaocheng/font/fontello.svg
XinshouZhinanDvwa19QuanJibieJiaocheng/font/fontello.ttf
XinshouZhinanDvwa19QuanJibieJiaocheng/font/fontello.woff
XinshouZhinanDvwa19QuanJibieJiaocheng/img/__init__.py
XinshouZhinanDvwa19QuanJibieJiaocheng/img/annotator-glyph-sprite.png
XinshouZhinanDvwa19QuanJibieJiaocheng/img/annotator-icon-sprite.png
XinshouZhinanDvwa19QuanJibieJiaocheng/img/apple-touch-icon.png
XinshouZhinanDvwa19QuanJibieJiaocheng/img/cancelfullscreen.png
XinshouZhinanDvwa19QuanJibieJiaocheng/img/close.png
XinshouZhinanDvwa19QuanJibieJiaocheng/img/fullscreen.png
XinshouZhinanDvwa19QuanJibieJiaocheng/img/loader.gif
XinshouZhinanDvwa19QuanJibieJiaocheng/img/menu-icon.png
XinshouZhinanDvwa19QuanJibieJiaocheng/img/save.png
XinshouZhinanDvwa19QuanJibieJiaocheng/img/saved.png
XinshouZhinanDvwa19QuanJibieJiaocheng/img/settings-s.png
XinshouZhinanDvwa19QuanJibieJiaocheng/img/settings.png
XinshouZhinanDvwa19QuanJibieJiaocheng/img/star.png
XinshouZhinanDvwa19QuanJibieJiaocheng/js/__init__.py
XinshouZhinanDvwa19QuanJibieJiaocheng/js/epub.js
XinshouZhinanDvwa19QuanJibieJiaocheng/js/epub.min.js
XinshouZhinanDvwa19QuanJibieJiaocheng/js/epub.min.map
XinshouZhinanDvwa19QuanJibieJiaocheng/js/hooks.min.js
XinshouZhinanDvwa19QuanJibieJiaocheng/js/hooks.min.map
XinshouZhinanDvwa19QuanJibieJiaocheng/js/reader.js
xinshou_zhinan_dvwa_1_9_quan_jibie_jiaocheng-2024.3.2.0.dist-info/METADATA
xinshou_zhinan_dvwa_1_9_quan_jibie_jiaocheng-2024.3.2.0.dist-info/WHEEL
xinshou_zhinan_dvwa_1_9_quan_jibie_jiaocheng-2024.3.2.0.dist-info/entry_points.txt
xinshou_zhinan_dvwa_1_9_quan_jibie_jiaocheng-2024.3.2.0.dist-info/top_level.txt
xinshou_zhinan_dvwa_1_9_quan_jibie_jiaocheng-2024.3.2.0.dist-info/RECORD
